extract_favicon/VERSION.md
extract_favicon/__init__.py
extract_favicon/config.py
extract_favicon/loader.py
extract_favicon/main.py
extract_favicon/main_async.py
extract_favicon/utils.py
extract_favicon-0.5.4.dist-info/METADATA
extract_favicon-0.5.4.dist-info/WHEEL
extract_favicon-0.5.4.dist-info/licenses/LICENSE
extract_favicon-0.5.4.dist-info/RECORD
