Metadata-Version: 2.4
Name: extract-favicon
Version: 0.5.4
Summary: Find and extract the favicon of any website
Project-URL: Homepage, https://alexmili.github.io/extract_favicon
Project-URL: Issues, https://github.com/AlexMili/Extract_Favicon/issues
Project-URL: Repository, https://github.com/AlexMili/Extract_Favicon
Project-URL: Documentation, https://alexmili.github.io/extract_favicon
Author: Alex Mili
License: MIT License
License-File: LICENSE
Classifier: Intended Audience :: Developers
Classifier: License :: OSI Approved :: MIT License
Requires-Python: >=3.9
Requires-Dist: beautifulsoup4>=4.13.0
Requires-Dist: defusedxml>=0.7.1
Requires-Dist: pillow
Requires-Dist: reachable>=0.9.1
Requires-Dist: tldextract
